{"brawlhalla_id": 2493817, "name": "MadMax", "xp": 3031926, "level": 100, "xp_percentage": 0, "games": 27871, "wins": 16200, "damagebomb": "18798", "damagemine": "12266", "damagespikeball": "8294", "damagesidekick": "14011", "hitsnowball": 483, "kobomb": 211, "komine": 122, "kospikeball": 83, "kosidekick": 5, "kosnowball": 203, "legends": [{"legend_id": 8, "legend_name_key": "queen nai", "damagedealt": "74554", "damagetaken": "49042", "kos": 371, "falls": 245, "suicides": 17, "teamkos": 5, "matchtime": 23605, "games": 130, "wins": 95, "damageunarmed": "5892", "damagethrownitem": "1151", "damageweaponone": "38962", "damageweapontwo": "24898", "damagegadgets": "2674", "kounarmed": 42, "kothrownitem": 8, "koweaponone": 168, "koweapontwo": 136, "kogadgets": 12, "timeheldweaponone": 10452, "timeheldweapontwo": 7885, "xp": 16804, "level": 16, "xp_percentage": 0.38304482911673}, {"legend_id": 20, "legend_name_key": "asuri", "damagedealt": "380663", "damagetaken": "336218", "kos": 1835, "falls": 1660, "suicides": 71, "teamkos": 5, "matchtime": 144813, "games": 775, "wins": 456, "damageunarmed": "29610", "damagethrownitem": "6751", "damageweaponone": "187466", "damageweapontwo": "149008", "damagegadgets": "3000", "kounarmed": 150, "kothrownitem": 101, "koweaponone": 770, "koweapontwo": 774, "kogadgets": 29, "timeheldweaponone": 64026, "timeheldweapontwo": 51754, "xp": 82059, "level": 33, "xp_percentage": 0.083589743589744}, {"legend_id": 29, "legend_name_key": "wu shang", "damagedealt": "76905", "damagetaken": "61167", "kos": 390, "falls": 301, "suicides": 16, "teamkos": 1, "matchtime": 27063, "games": 159, "wins": 99, "damageunarmed": "8243", "damagethrownitem": "1343", "damageweaponone": "29822", "damageweapontwo": "36406", "damagegadgets": "454", "kounarmed": 58, "kothrownitem": 26, "koweaponone": 127, "koweapontwo": 174, "kogadgets": 3, "timeheldweaponone": 10087, "timeheldweapontwo": 10477, "xp": 15711, "level": 15, "xp_percentage": 0.88942307692308}, {"legend_id": 6, "legend_name_key": "lord vraxx", "damagedealt": "87663", "damagetaken": "70092", "kos": 445, "falls": 357, "suicides": 26, "teamkos": 1, "matchtime": 30771, "games": 182, "wins": 112, "damageunarmed": "6251", "damagethrownitem": "790", "damageweaponone": "51084", "damageweapontwo": "28468", "damagegadgets": "451", "kounarmed": 30, "kothrownitem": 23, "koweaponone": 251, "koweapontwo": 139, "kogadgets": 1, "timeheldweaponone": 15087, "timeheldweapontwo": 9389, "xp": 18795, "level": 17, "xp_percentage": 0.24763081994232}, {"legend_id": 28, "legend_name_key": "kor", "damagedealt": "67264", "damagetaken": "54477", "kos": 384, "falls": 263, "suicides": 14, "teamkos": 1, "matchtime": 23417, "games": 136, "wins": 93, "damageunarmed": "6277", "damagethrownitem": "1171", "damageweaponone": "28706", "damageweapontwo": "30286", "damagegadgets": "193", "kounarmed": 35, "kothrownitem": 28, "koweaponone": 168, "koweapontwo": 150, "kogadgets": 3, "timeheldweaponone": 9359, "timeheldweapontwo": 8823, "xp": 14666, "level": 15, "xp_percentage": 0.38701923076923}, {"legend_id": 33, "legend_name_key": "mirage", "damagedealt": "259645", "damagetaken": "220090", "kos": 1246, "falls": 1093, "suicides": 53, "teamkos": 3, "matchtime": 93550, "games": 528, "wins": 322, "damageunarmed": "20079", "damagethrownitem": "4364", "damageweaponone": "118584", "damageweapontwo": "112614", "damagegadgets": "1617", "kounarmed": 112, "kothrownitem": 103, "koweaponone": 502, "koweapontwo": 513, "kogadgets": 13, "timeheldweaponone": 39365, "timeheldweapontwo": 34318, "xp": 54797, "level": 27, "xp_percentage": 0.76361192023303}, {"legend_id": 18, "legend_name_key": "ember", "damagedealt": "42846", "damagetaken": "30187", "kos": 200, "falls": 154, "suicides": 14, "teamkos": 0, "matchtime": 12890, "games": 80, "wins": 50, "damageunarmed": "3444", "damagethrownitem": "565", "damageweaponone": "23724", "damageweapontwo": "14030", "damagegadgets": "437", "kounarmed": 17, "kothrownitem": 5, "koweaponone": 111, "koweapontwo": 66, "kogadgets": 1, "timeheldweaponone": 6106, "timeheldweapontwo": 3958, "xp": 7832, "level": 11, "xp_percentage": 0.43566433566434}, {"legend_id": 26, "legend_name_key": "jhala", "damagedealt": "356419", "damagetaken": "326431", "kos": 1732, "falls": 1637, "suicides": 47, "teamkos": 13, "matchtime": 138940, "games": 758, "wins": 419, "damageunarmed": "33252", "damagethrownitem": "5945", "damageweaponone": "181334", "damageweapontwo": "129028", "damagegadgets": "3053", "kounarmed": 150, "kothrownitem": 106, "koweaponone": 789, "koweapontwo": 652, "kogadgets": 29, "timeheldweaponone": 59900, "timeheldweapontwo": 48721, "xp": 77475, "level": 32, "xp_percentage": 0.27031361368496}, {"legend_id": 4, "legend_name_key": "cassidy", "damagedealt": "184747", "damagetaken": "158722", "kos": 968, "falls": 810, "suicides": 49, "teamkos": 14, "matchtime": 63982, "games": 388, "wins": 229, "damageunarmed": "13197", "damagethrownitem": "2363", "damageweaponone": "64357", "damageweapontwo": "102722", "damagegadgets": "688", "kounarmed": 67, "kothrownitem": 71, "koweaponone": 320, "koweapontwo": 505, "kogadgets": 4, "timeheldweaponone": 20420, "timeheldweapontwo": 30372, "xp": 37610, "level": 23, "xp_percentage": 0.53316749585406}, {"legend_id": 10, "legend_name_key": "hattori", "damagedealt": "567427", "damagetaken": "505097", "kos": 2622, "falls": 2515, "suicides": 99, "teamkos": 8, "matchtime": 221711, "games": 1129, "wins": 611, "damageunarmed": "40780", "damagethrownitem": "9560", "damageweaponone": "256828", "damageweapontwo": "227644", "damagegadgets": "26261", "kounarmed": 238, "kothrownitem": 162, "koweaponone": 1207, "koweapontwo": 837, "kogadgets": 168, "timeheldweaponone": 97745, "timeheldweapontwo": 75413, "xp": 121814, "level": 39, "xp_percentage": 0.21199671322925}, {"legend_id": 19, "legend_name_key": "brynn", "damagedealt": "3969975", "damagetaken": "3522958", "kos": 18748, "falls": 17289, "suicides": 259, "teamkos": 55, "matchtime": 1422663, "games": 8025, "wins": 4543, "damageunarmed": "262629", "damagethrownitem": "73470", "damageweaponone": "2047254", "damageweapontwo": "1555431", "damagegadgets": "1653", "kounarmed": 1205, "kothrownitem": 1238, "koweaponone": 8793, "koweapontwo": 7474, "kogadgets": 8, "timeheldweaponone": 633251, "timeheldweapontwo": 489651, "xp": 919819, "level": 93, "xp_percentage": 0.050752041254835}, {"legend_id": 38, "legend_name_key": "caspian", "damagedealt": "104380", "damagetaken": "87139", "kos": 536, "falls": 445, "suicides": 36, "teamkos": 3, "matchtime": 36534, "games": 216, "wins": 143, "damageunarmed": "7736", "damagethrownitem": "1497", "damageweaponone": "52199", "damageweapontwo": "40611", "damagegadgets": "894", "kounarmed": 48, "kothrownitem": 14, "koweaponone": 322, "koweapontwo": 138, "kogadgets": 10, "timeheldweaponone": 14129, "timeheldweapontwo": 14822, "xp": 21911, "level": 18, "xp_percentage": 0.49199084668192}, {"legend_id": 12, "legend_name_key": "scarlet", "damagedealt": "218229", "damagetaken": "176848", "kos": 1128, "falls": 875, "suicides": 35, "teamkos": 9, "matchtime": 77911, "games": 446, "wins": 283, "damageunarmed": "14482", "damagethrownitem": "3232", "damageweaponone": "71312", "damageweapontwo": "123066", "damagegadgets": "4470", "kounarmed": 60, "kothrownitem": 102, "koweaponone": 403, "koweapontwo": 534, "kogadgets": 26, "timeheldweaponone": 22531, "timeheldweapontwo": 39421, "xp": 44990, "level": 25, "xp_percentage": 0.46600496277916}, {"legend_id": 30, "legend_name_key": "val", "damagedealt": "130033", "damagetaken": "113693", "kos": 625, "falls": 564, "suicides": 24, "teamkos": 3, "matchtime": 51855, "games": 263, "wins": 150, "damageunarmed": "7874", "damagethrownitem": "1591", "damageweaponone": "64670", "damageweapontwo": "47695", "damagegadgets": "6733", "kounarmed": 30, "kothrownitem": 26, "koweaponone": 301, "koweapontwo": 227, "kogadgets": 39, "timeheldweaponone": 24061, "timeheldweapontwo": 18147, "xp": 27967, "level": 20, "xp_percentage": 0.63313413014608}, {"legend_id": 3, "legend_name_key": "bodvar", "damagedealt": "230704", "damagetaken": "199869", "kos": 1183, "falls": 989, "suicides": 44, "teamkos": 7, "matchtime": 85190, "games": 471, "wins": 284, "damageunarmed": "18806", "damagethrownitem": "3670", "damageweaponone": "131909", "damageweapontwo": "72234", "damagegadgets": "1966", "kounarmed": 99, "kothrownitem": 81, "koweaponone": 641, "koweapontwo": 342, "kogadgets": 17, "timeheldweaponone": 43466, "timeheldweapontwo": 24150, "xp": 48811, "level": 26, "xp_percentage": 0.39298328231693}, {"legend_id": 35, "legend_name_key": "mordex", "damagedealt": "311530", "damagetaken": "252455", "kos": 1565, "falls": 1305, "suicides": 113, "teamkos": 1, "matchtime": 113119, "games": 629, "wins": 380, "damageunarmed": "24491", "damagethrownitem": "4565", "damageweaponone": "166369", "damageweapontwo": "110788", "damagegadgets": "2279", "kounarmed": 151, "kothrownitem": 90, "koweaponone": 731, "koweapontwo": 560, "kogadgets": 25, "timeheldweaponone": 53948, "timeheldweapontwo": 36261, "xp": 65267, "level": 29, "xp_percentage": 0.96278975193168}, {"legend_id": 5, "legend_name_key": "orion", "damagedealt": "62700", "damagetaken": "46438", "kos": 314, "falls": 224, "suicides": 9, "teamkos": 0, "matchtime": 18772, "games": 125, "wins": 84, "damageunarmed": "4831", "damagethrownitem": "628", "damageweaponone": "33282", "damageweapontwo": "22919", "damagegadgets": "598", "kounarmed": 23, "kothrownitem": 16, "koweaponone": 158, "koweapontwo": 115, "kogadgets": 1, "timeheldweaponone": 9271, "timeheldweapontwo": 5417, "xp": 11779, "level": 13, "xp_percentage": 0.89901904212349}, {"legend_id": 34, "legend_name_key": "nix", "damagedealt": "555620", "damagetaken": "475591", "kos": 2617, "falls": 2430, "suicides": 146, "teamkos": 12, "matchtime": 211244, "games": 1119, "wins": 627, "damageunarmed": "40667", "damagethrownitem": "6835", "damageweaponone": "262731", "damageweapontwo": "239925", "damagegadgets": "1112", "kounarmed": 241, "kothrownitem": 171, "koweaponone": 1026, "koweapontwo": 1162, "kogadgets": 11, "timeheldweaponone": 94028, "timeheldweapontwo": 78489, "xp": 112662, "level": 37, "xp_percentage": 0.92047626047332}, {"legend_id": 24, "legend_name_key": "koji", "damagedealt": "242685", "damagetaken": "214577", "kos": 1127, "falls": 1072, "suicides": 27, "teamkos": 4, "matchtime": 87816, "games": 491, "wins": 267, "damageunarmed": "13615", "damagethrownitem": "2563", "damageweaponone": "142764", "damageweapontwo": "81269", "damagegadgets": "688", "kounarmed": 78, "kothrownitem": 40, "koweaponone": 623, "koweapontwo": 377, "kogadgets": 6, "timeheldweaponone": 44147, "timeheldweapontwo": 27514, "xp": 53997, "level": 27, "xp_percentage": 0.58436029576518}, {"legend_id": 25, "legend_name_key": "diana", "damagedealt": "623321", "damagetaken": "544393", "kos": 2844, "falls": 2751, "suicides": 78, "teamkos": 6, "matchtime": 225409, "games": 1261, "wins": 683, "damageunarmed": "40793", "damagethrownitem": "4760", "damageweaponone": "256625", "damageweapontwo": "316156", "damagegadgets": "993", "kounarmed": 212, "kothrownitem": 118, "koweaponone": 1091, "koweapontwo": 1406, "kogadgets": 10, "timeheldweaponone": 81787, "timeheldweapontwo": 101828, "xp": 135256, "level": 41, "xp_percentage": 0.016153846153846}, {"legend_id": 11, "legend_name_key": "sir roland", "damagedealt": "117257", "damagetaken": "95883", "kos": 565, "falls": 467, "suicides": 18, "teamkos": 8, "matchtime": 45906, "games": 229, "wins": 139, "damageunarmed": "9051", "damagethrownitem": "1489", "damageweaponone": "63228", "damageweapontwo": "37846", "damagegadgets": "4662", "kounarmed": 41, "kothrownitem": 36, "koweaponone": 280, "koweapontwo": 181, "kogadgets": 26, "timeheldweaponone": 22262, "timeheldweapontwo": 14407, "xp": 24286, "level": 19, "xp_percentage": 0.37025204117856}, {"legend_id": 31, "legend_name_key": "ragnir", "damagedealt": "136994", "damagetaken": "114736", "kos": 677, "falls": 609, "suicides": 62, "teamkos": 6, "matchtime": 49209, "games": 280, "wins": 159, "damageunarmed": "13308", "damagethrownitem": "1981", "damageweaponone": "62200", "damageweapontwo": "57464", "damagegadgets": "646", "kounarmed": 54, "kothrownitem": 34, "koweaponone": 282, "koweapontwo": 299, "kogadgets": 3, "timeheldweaponone": 21002, "timeheldweapontwo": 17386, "xp": 27586, "level": 20, "xp_percentage": 0.5066401062417}, {"legend_id": 37, "legend_name_key": "artemis", "damagedealt": "120939", "damagetaken": "91122", "kos": 606, "falls": 457, "suicides": 36, "teamkos": 9, "matchtime": 43421, "games": 218, "wins": 147, "damageunarmed": "9608", "damagethrownitem": "1546", "damageweaponone": "53336", "damageweapontwo": "52680", "damagegadgets": "2797", "kounarmed": 56, "kothrownitem": 42, "koweaponone": 273, "koweapontwo": 213, "kogadgets": 22, "timeheldweaponone": 16674, "timeheldweapontwo": 17952, "xp": 24361, "level": 19, "xp_percentage": 0.39687610933617}, {"legend_id": 39, "legend_name_key": "sidra", "damagedealt": "282784", "damagetaken": "234630", "kos": 1330, "falls": 1177, "suicides": 52, "teamkos": 3, "matchtime": 105622, "games": 568, "wins": 335, "damageunarmed": "22603", "damagethrownitem": "4088", "damageweaponone": "179484", "damageweapontwo": "72527", "damagegadgets": "1211", "kounarmed": 124, "kothrownitem": 90, "koweaponone": 688, "koweapontwo": 412, "kogadgets": 13, "timeheldweaponone": 57563, "timeheldweapontwo": 26958, "xp": 65262, "level": 29, "xp_percentage": 0.96177307848719}, {"legend_id": 23, "legend_name_key": "azoth", "damagedealt": "78022", "damagetaken": "62253", "kos": 371, "falls": 303, "suicides": 10, "teamkos": 3, "matchtime": 25225, "games": 141, "wins": 85, "damageunarmed": "5599", "damagethrownitem": "704", "damageweaponone": "43193", "damageweapontwo": "27716", "damagegadgets": "307", "kounarmed": 37, "kothrownitem": 12, "koweaponone": 191, "koweapontwo": 125, "kogadgets": 6, "timeheldweaponone": 12618, "timeheldweapontwo": 7421, "xp": 15940, "level": 15, "xp_percentage": 0.99951923076923}, {"legend_id": 36, "legend_name_key": "yumiko", "damagedealt": "72678", "damagetaken": "63892", "kos": 343, "falls": 314, "suicides": 9, "teamkos": 0, "matchtime": 26350, "games": 151, "wins": 86, "damageunarmed": "5659", "damagethrownitem": "822", "damageweaponone": "34883", "damageweapontwo": "30421", "damagegadgets": "338", "kounarmed": 39, "kothrownitem": 19, "koweaponone": 130, "koweapontwo": 152, "kogadgets": 3, "timeheldweaponone": 10903, "timeheldweapontwo": 10046, "xp": 16226, "level": 16, "xp_percentage": 0.12649800266312}, {"legend_id": 40, "legend_name_key": "xull", "damagedealt": "216779", "damagetaken": "166930", "kos": 1029, "falls": 850, "suicides": 45, "teamkos": 6, "matchtime": 70493, "games": 420, "wins": 270, "damageunarmed": "20277", "damagethrownitem": "3335", "damageweaponone": "121981", "damageweapontwo": "68013", "damagegadgets": "1346", "kounarmed": 106, "kothrownitem": 74, "koweaponone": 502, "koweapontwo": 336, "kogadgets": 10, "timeheldweaponone": 34905, "timeheldweapontwo": 19645, "xp": 42308, "level": 24, "xp_percentage": 0.78914240755311}, {"legend_id": 9, "legend_name_key": "lucien", "damagedealt": "383162", "damagetaken": "319675", "kos": 1830, "falls": 1561, "suicides": 65, "teamkos": 20, "matchtime": 141016, "games": 731, "wins": 433, "damageunarmed": "20909", "damagethrownitem": "4149", "damageweaponone": "183349", "damageweapontwo": "169650", "damagegadgets": "1965", "kounarmed": 104, "kothrownitem": 46, "koweaponone": 943, "koweapontwo": 718, "kogadgets": 14, "timeheldweaponone": 59692, "timeheldweapontwo": 56952, "xp": 76320, "level": 32, "xp_percentage": 0.064504632929437}, {"legend_id": 7, "legend_name_key": "gnash", "damagedealt": "173107", "damagetaken": "163737", "kos": 881, "falls": 810, "suicides": 23, "teamkos": 10, "matchtime": 64501, "games": 364, "wins": 209, "damageunarmed": "12164", "damagethrownitem": "3350", "damageweaponone": "92957", "damageweapontwo": "62710", "damagegadgets": "461", "kounarmed": 66, "kothrownitem": 53, "koweaponone": 509, "koweapontwo": 250, "kogadgets": 1, "timeheldweaponone": 30766, "timeheldweapontwo": 20053, "xp": 42228, "level": 24, "xp_percentage": 0.76816155258327}, {"legend_id": 13, "legend_name_key": "thatch", "damagedealt": "227655", "damagetaken": "187877", "kos": 1163, "falls": 907, "suicides": 27, "teamkos": 5, "matchtime": 77962, "games": 470, "wins": 301, "damageunarmed": "14338", "damagethrownitem": "2136", "damageweaponone": "74742", "damageweapontwo": "133870", "damagegadgets": "939", "kounarmed": 78, "kothrownitem": 30, "koweaponone": 382, "koweapontwo": 664, "kogadgets": 8, "timeheldweaponone": 22504, "timeheldweapontwo": 41201, "xp": 48147, "level": 26, "xp_percentage": 0.23663762655992}, {"legend_id": 42, "legend_name_key": "kaya", "damagedealt": "132636", "damagetaken": "115150", "kos": 587, "falls": 561, "suicides": 9, "teamkos": 4, "matchtime": 50395, "games": 254, "wins": 139, "damageunarmed": "8049", "damagethrownitem": "1941", "damageweaponone": "61880", "damageweapontwo": "58788", "damagegadgets": "913", "kounarmed": 39, "kothrownitem": 29, "koweaponone": 253, "koweapontwo": 258, "kogadgets": 8, "timeheldweaponone": 21208, "timeheldweapontwo": 19218, "xp": 27188, "level": 20, "xp_percentage": 0.37450199203187}, {"legend_id": 15, "legend_name_key": "sentinel", "damagedealt": "39601", "damagetaken": "28611", "kos": 210, "falls": 144, "suicides": 10, "teamkos": 0, "matchtime": 12610, "games": 71, "wins": 45, "damageunarmed": "2674", "damagethrownitem": "638", "damageweaponone": "22428", "damageweapontwo": "12820", "damagegadgets": "654", "kounarmed": 15, "kothrownitem": 5, "koweaponone": 105, "koweapontwo": 80, "kogadgets": 2, "timeheldweaponone": 6381, "timeheldweapontwo": 3704, "xp": 8112, "level": 11, "xp_percentage": 0.63146853146853}, {"legend_id": 22, "legend_name_key": "ulgrim", "damagedealt": "179402", "damagetaken": "162308", "kos": 865, "falls": 807, "suicides": 17, "teamkos": 4, "matchtime": 65365, "games": 375, "wins": 216, "damageunarmed": "12417", "damagethrownitem": "2671", "damageweaponone": "73690", "damageweapontwo": "89202", "damagegadgets": "220", "kounarmed": 69, "kothrownitem": 56, "koweaponone": 370, "koweapontwo": 369, "kogadgets": 1, "timeheldweaponone": 23607, "timeheldweapontwo": 27968, "xp": 41598, "level": 24, "xp_percentage": 0.60293731969578}, {"legend_id": 32, "legend_name_key": "cross", "damagedealt": "43122", "damagetaken": "35069", "kos": 206, "falls": 175, "suicides": 11, "teamkos": 0, "matchtime": 15463, "games": 81, "wins": 49, "damageunarmed": "3499", "damagethrownitem": "575", "damageweaponone": "22806", "damageweapontwo": "15417", "damagegadgets": "445", "kounarmed": 22, "kothrownitem": 4, "koweaponone": 95, "koweapontwo": 83, "kogadgets": 1, "timeheldweaponone": 6920, "timeheldweapontwo": 5406, "xp": 9280, "level": 12, "xp_percentage": 0.40518331226296}, {"legend_id": 14, "legend_name_key": "ada", "damagedealt": "235704", "damagetaken": "210771", "kos": 1129, "falls": 1045, "suicides": 28, "teamkos": 4, "matchtime": 86510, "games": 478, "wins": 255, "damageunarmed": "17109", "damagethrownitem": "3143", "damageweaponone": "120380", "damageweapontwo": "92234", "damagegadgets": "1089", "kounarmed": 92, "kothrownitem": 56, "koweaponone": 604, "koweapontwo": 367, "kogadgets": 7, "timeheldweaponone": 39352, "timeheldweapontwo": 29292, "xp": 46931, "level": 25, "xp_percentage": 0.94764267990074}, {"legend_id": 21, "legend_name_key": "barraza", "damagedealt": "491325", "damagetaken": "427342", "kos": 2391, "falls": 2084, "suicides": 37, "teamkos": 16, "matchtime": 176640, "games": 989, "wins": 574, "damageunarmed": "27208", "damagethrownitem": "5096", "damageweaponone": "226405", "damageweapontwo": "228690", "damagegadgets": "575", "kounarmed": 127, "kothrownitem": 90, "koweaponone": 1163, "koweapontwo": 1001, "kogadgets": 2, "timeheldweaponone": 69188, "timeheldweapontwo": 76167, "xp": 104977, "level": 36, "xp_percentage": 0.78324447829398}, {"legend_id": 16, "legend_name_key": "teros", "damagedealt": "283027", "damagetaken": "229241", "kos": 1433, "falls": 1133, "suicides": 35, "teamkos": 14, "matchtime": 90130, "games": 557, "wins": 340, "damageunarmed": "19257", "damagethrownitem": "5125", "damageweaponone": "120062", "damageweapontwo": "135422", "damagegadgets": "1124", "kounarmed": 105, "kothrownitem": 99, "koweaponone": 601, "koweapontwo": 623, "kogadgets": 5, "timeheldweaponone": 33535, "timeheldweapontwo": 37267, "xp": 54785, "level": 27, "xp_percentage": 0.76092314586601}, {"legend_id": 43, "legend_name_key": "jiro", "damagedealt": "240013", "damagetaken": "208538", "kos": 1119, "falls": 1039, "suicides": 45, "teamkos": 3, "matchtime": 91633, "games": 459, "wins": 257, "damageunarmed": "22704", "damagethrownitem": "4413", "damageweaponone": "63632", "damageweapontwo": "143840", "damagegadgets": "2831", "kounarmed": 126, "kothrownitem": 94, "koweaponone": 333, "koweapontwo": 536, "kogadgets": 22, "timeheldweaponone": 21701, "timeheldweapontwo": 49462, "xp": 50879, "level": 26, "xp_percentage": 0.87991523428302}, {"legend_id": 41, "legend_name_key": "isaiah", "damagedealt": "244252", "damagetaken": "196454", "kos": 1219, "falls": 961, "suicides": 40, "teamkos": 5, "matchtime": 85604, "games": 486, "wins": 313, "damageunarmed": "16286", "damagethrownitem": "2697", "damageweaponone": "123560", "damageweapontwo": "97717", "damagegadgets": "2005", "kounarmed": 101, "kothrownitem": 80, "koweaponone": 426, "koweapontwo": 593, "kogadgets": 17, "timeheldweaponone": 38005, "timeheldweapontwo": 31243, "xp": 50636, "level": 26, "xp_percentage": 0.82269837532376}, {"legend_id": 44, "legend_name_key": "lin fei", "damagedealt": "129724", "damagetaken": "100614", "kos": 620, "falls": 514, "suicides": 31, "teamkos": 0, "matchtime": 43478, "games": 259, "wins": 163, "damageunarmed": "10303", "damagethrownitem": "1427", "damageweaponone": "58821", "damageweapontwo": "57361", "damagegadgets": "508", "kounarmed": 51, "kothrownitem": 29, "koweaponone": 301, "koweapontwo": 234, "kogadgets": 2, "timeheldweaponone": 17763, "timeheldweapontwo": 16548, "xp": 25746, "level": 19, "xp_percentage": 0.88853390131345}, {"legend_id": 46, "legend_name_key": "rayman", "damagedealt": "98762", "damagetaken": "79210", "kos": 504, "falls": 401, "suicides": 23, "teamkos": 2, "matchtime": 35065, "games": 197, "wins": 123, "damageunarmed": "9469", "damagethrownitem": "1716", "damageweaponone": "46420", "damageweapontwo": "39916", "damagegadgets": "481", "kounarmed": 48, "kothrownitem": 27, "koweaponone": 205, "koweapontwo": 220, "kogadgets": 3, "timeheldweaponone": 15710, "timeheldweapontwo": 11607, "xp": 20961, "level": 18, "xp_percentage": 0.12967200610221}, {"legend_id": 45, "legend_name_key": "zariel", "damagedealt": "26881", "damagetaken": "21683", "kos": 134, "falls": 108, "suicides": 5, "teamkos": 0, "matchtime": 9690, "games": 58, "wins": 39, "damageunarmed": "2584", "damagethrownitem": "381", "damageweaponone": "9749", "damageweapontwo": "13759", "damagegadgets": "121", "kounarmed": 13, "kothrownitem": 6, "koweaponone": 54, "koweapontwo": 60, "kogadgets": 0, "timeheldweaponone": 3109, "timeheldweapontwo": 4310, "xp": 5933, "level": 10, "xp_percentage": 0.0015649452269171}, {"legend_id": 47, "legend_name_key": "dusk", "damagedealt": "32059", "damagetaken": "25593", "kos": 142, "falls": 122, "suicides": 6, "teamkos": 0, "matchtime": 10888, "games": 64, "wins": 40, "damageunarmed": "3570", "damagethrownitem": "468", "damageweaponone": "9439", "damageweapontwo": "18294", "damagegadgets": "97", "kounarmed": 25, "kothrownitem": 9, "koweaponone": 42, "koweapontwo": 65, "kogadgets": 1, "timeheldweaponone": 2887, "timeheldweapontwo": 5562, "xp": 6213, "level": 10, "xp_percentage": 0.22065727699531}, {"legend_id": 48, "legend_name_key": "fait", "damagedealt": "209745", "damagetaken": "166242", "kos": 1011, "falls": 846, "suicides": 61, "teamkos": 0, "matchtime": 70624, "games": 419, "wins": 260, "damageunarmed": "12321", "damagethrownitem": "2023", "damageweaponone": "109656", "damageweapontwo": "83445", "damagegadgets": "767", "kounarmed": 73, "kothrownitem": 39, "koweaponone": 443, "koweapontwo": 443, "kogadgets": 10, "timeheldweaponone": 33759, "timeheldweapontwo": 24411, "xp": 45316, "level": 25, "xp_percentage": 0.5468982630273}, {"legend_id": 50, "legend_name_key": "petra", "damagedealt": "592506", "damagetaken": "505622", "kos": 2976, "falls": 2539, "suicides": 93, "teamkos": 11, "matchtime": 209822, "games": 1218, "wins": 721, "damageunarmed": "36582", "damagethrownitem": "7336", "damageweaponone": "276100", "damageweapontwo": "265616", "damagegadgets": "1108", "kounarmed": 171, "kothrownitem": 144, "koweaponone": 1502, "koweapontwo": 1141, "kogadgets": 9, "timeheldweaponone": 92096, "timeheldweapontwo": 79584, "xp": 121190, "level": 39, "xp_percentage": 0.126540673788}, {"legend_id": 49, "legend_name_key": "thor", "damagedealt": "254789", "damagetaken": "217850", "kos": 1275, "falls": 1072, "suicides": 32, "teamkos": 4, "matchtime": 89554, "games": 517, "wins": 300, "damageunarmed": "19448", "damagethrownitem": "3533", "damageweaponone": "132785", "damageweapontwo": "96450", "damagegadgets": "478", "kounarmed": 101, "kothrownitem": 87, "koweaponone": 734, "koweapontwo": 345, "kogadgets": 2, "timeheldweaponone": 40683, "timeheldweapontwo": 30389, "xp": 51883, "level": 27, "xp_percentage": 0.1106878781089}, {"legend_id": 51, "legend_name_key": "vector", "damagedealt": "16345", "damagetaken": "14888", "kos": 84, "falls": 74, "suicides": 2, "teamkos": 0, "matchtime": 6272, "games": 38, "wins": 25, "damageunarmed": "1714", "damagethrownitem": "129", "damageweaponone": "8298", "damageweapontwo": "5885", "damagegadgets": "148", "kounarmed": 8, "kothrownitem": 5, "koweaponone": 43, "koweapontwo": 26, "kogadgets": 1, "timeheldweaponone": 2863, "timeheldweapontwo": 1885, "xp": 4048, "level": 8, "xp_percentage": 0.24172517552658}, {"legend_id": 52, "legend_name_key": "volkov", "damagedealt": "159689", "damagetaken": "124148", "kos": 825, "falls": 610, "suicides": 44, "teamkos": 1, "matchtime": 56715, "games": 341, "wins": 232, "damageunarmed": "13266", "damagethrownitem": "2625", "damageweaponone": "47248", "damageweapontwo": "94066", "damagegadgets": "475", "kounarmed": 73, "kothrownitem": 56, "koweaponone": 216, "koweapontwo": 467, "kogadgets": 6, "timeheldweaponone": 13511, "timeheldweapontwo": 31772, "xp": 34084, "level": 22, "xp_percentage": 0.53057025279248}, {"legend_id": 53, "legend_name_key": "onyx", "damagedealt": "68680", "damagetaken": "52374", "kos": 370, "falls": 257, "suicides": 13, "teamkos": 1, "matchtime": 22832, "games": 145, "wins": 96, "damageunarmed": "4621", "damagethrownitem": "757", "damageweaponone": "24225", "damageweapontwo": "38395", "damagegadgets": "261", "kounarmed": 38, "kothrownitem": 26, "koweaponone": 142, "koweapontwo": 163, "kogadgets": 1, "timeheldweaponone": 7665, "timeheldweapontwo": 10792, "xp": 13448, "level": 14, "xp_percentage": 0.78342947037231}, {"legend_id": 54, "legend_name_key": "jaeyun", "damagedealt": "114788", "damagetaken": "95693", "kos": 581, "falls": 466, "suicides": 4, "teamkos": 3, "matchtime": 38884, "games": 230, "wins": 144, "damageunarmed": "6969", "damagethrownitem": "955", "damageweaponone": "27450", "damageweapontwo": "78220", "damagegadgets": "178", "kounarmed": 35, "kothrownitem": 12, "koweaponone": 139, "koweapontwo": 392, "kogadgets": 2, "timeheldweaponone": 8109, "timeheldweapontwo": 23706, "xp": 26005, "level": 19, "xp_percentage": 0.98047568335108}, {"legend_id": 55, "legend_name_key": "mako", "damagedealt": "38400", "damagetaken": "29462", "kos": 209, "falls": 139, "suicides": 9, "teamkos": 1, "matchtime": 12313, "games": 76, "wins": 56, "damageunarmed": "2398", "damagethrownitem": "360", "damageweaponone": "14159", "damageweapontwo": "20925", "damagegadgets": "72", "kounarmed": 11, "kothrownitem": 4, "koweaponone": 71, "koweapontwo": 122, "kogadgets": 0, "timeheldweaponone": 4099, "timeheldweapontwo": 6115, "xp": 8239, "level": 11, "xp_percentage": 0.72027972027972}, {"legend_id": 56, "legend_name_key": "magyar", "damagedealt": "3760", "damagetaken": "2616", "kos": 19, "falls": 12, "suicides": 0, "teamkos": 0, "matchtime": 1267, "games": 8, "wins": 8, "damageunarmed": "98", "damagethrownitem": "20", "damageweaponone": "2546", "damageweapontwo": "1066", "damagegadgets": "14", "kounarmed": 0, "kothrownitem": 1, "koweaponone": 14, "koweapontwo": 4, "kogadgets": 0, "timeheldweaponone": 745, "timeheldweapontwo": 355, "xp": 946, "level": 3, "xp_percentage": 0.80879120879121}, {"legend_id": 57, "legend_name_key": "reno", "damagedealt": "1687", "damagetaken": "1130", "kos": 10, "falls": 4, "suicides": 0, "teamkos": 0, "matchtime": 637, "games": 3, "wins": 3, "damageunarmed": "16", "damagethrownitem": "5", "damageweaponone": "864", "damageweapontwo": "798", "damagegadgets": "0", "kounarmed": 1, "kothrownitem": 0, "koweaponone": 3, "koweapontwo": 6, "kogadgets": 0, "timeheldweaponone": 375, "timeheldweapontwo": 223, "xp": 591, "level": 3, "xp_percentage": 0.028571428571429}, {"legend_id": 58, "legend_name_key": "munin", "damagedealt": "693", "damagetaken": "709", "kos": 2, "falls": 4, "suicides": 0, "teamkos": 0, "matchtime": 266, "games": 2, "wins": 1, "damageunarmed": "18", "damagethrownitem": "11", "damageweaponone": "275", "damageweapontwo": "372", "damagegadgets": "15", "kounarmed": 0, "kothrownitem": 1, "koweaponone": 0, "koweapontwo": 1, "kogadgets": 0, "timeheldweaponone": 111, "timeheldweapontwo": 113, "xp": 166, "level": 1, "xp_percentage": 0.79047619047619}, {"legend_id": 59, "legend_name_key": "arcadia", "damagedealt": "262", "damagetaken": "151", "kos": 2, "falls": 0, "suicides": 0, "teamkos": 0, "matchtime": 128, "games": 1, "wins": 1, "damageunarmed": "58", "damagethrownitem": "0", "damageweaponone": "155", "damageweapontwo": "48", "damagegadgets": "0", "kounarmed": 0, "kothrownitem": 0, "koweaponone": 2, "koweapontwo": 0, "kogadgets": 0, "timeheldweaponone": 48, "timeheldweapontwo": 13, "xp": 85, "level": 1, "xp_percentage": 0.4047619047619}, {"legend_id": 17, "legend_name_key": "redraptor", "damagedealt": "0", "damagetaken": "0", "kos": 0, "falls": 0, "suicides": 0, "teamkos": 0, "matchtime": 0, "games": 0, "wins": 0, "damageunarmed": "0", "damagethrownitem": "0", "damageweaponone": "0", "damageweapontwo": "0", "damagegadgets": "0", "kounarmed": 0, "kothrownitem": 0, "koweaponone": 0, "koweapontwo": 0, "kogadgets": 0, "timeheldweaponone": 0, "timeheldweapontwo": 0, "xp": 0, "level": 1, "xp_percentage": 0}, {"legend_id": 60, "legend_name_key": "ezio", "damagedealt": "0", "damagetaken": "0", "kos": 0, "falls": 0, "suicides": 0, "teamkos": 0, "matchtime": 0, "games": 0, "wins": 0, "damageunarmed": "0", "damagethrownitem": "0", "damageweaponone": "0", "damageweapontwo": "0", "damagegadgets": "0", "kounarmed": 0, "kothrownitem": 0, "koweaponone": 0, "koweapontwo": 0, "kogadgets": 0, "timeheldweaponone": 0, "timeheldweapontwo": 0, "xp": 0, "level": 1, "xp_percentage": 0}], "clan": {"clan_name": "Frost", "clan_id": 12, "clan_xp": "35646411", "personal_xp": 293503}}